gpt3discord.py
cogs/__init__.py
cogs/code_interpreter_service_cog.py
cogs/commands.py
cogs/image_service_cog.py
cogs/index_service_cog.py
cogs/moderations_service_cog.py
cogs/prompt_optimizer_cog.py
cogs/search_service_cog.py
cogs/text_service_cog.py
cogs/transcription_service_cog.py
cogs/translation_service_cog.py
models/__init__.py
models/autocomplete_model.py
models/check_model.py
models/deepl_model.py
models/embed_statics_model.py
models/image_understanding_model.py
models/index_model.py
models/openai_model.py
models/search_model.py
models/user_model.py
services/__init__.py
services/deletion_service.py
services/environment_service.py
services/health_service.py
services/image_service.py
services/message_queue_service.py
services/moderations_service.py
services/pickle_service.py
services/pinecone_service.py
services/sharegpt_service.py
services/text_service.py
services/usage_service.py
utils/__init__.py
utils/safe_ctx_respond.py
gpt3discord-12.3.8.dist-info/METADATA
gpt3discord-12.3.8.dist-info/WHEEL
gpt3discord-12.3.8.dist-info/entry_points.txt
gpt3discord-12.3.8.dist-info/licenses/LICENSE
gpt3discord-12.3.8.dist-info/RECORD
