Metadata-Version: 2.1
Name: gpt3discord
Version: 12.3.8
Summary: A Chat GPT Discord bot
Project-URL: Documentation, https://github.com/Kav-K/GPT3Discord/#readme
Project-URL: Issues, https://github.com/Kav-K/GPT3Discord/issues
Project-URL: Source, https://github.com/Kav-K/GPT3Discord
Author-email: Kaveen Kumarasinghe <contact@kaveenk.com>
License-Expression: MIT
License-File: LICENSE
Classifier: Development Status :: 4 - Beta
Classifier: Programming Language :: Python
Classifier: Programming Language :: Python :: 3.9
Requires-Python: >=3.9
Requires-Dist: aiofiles==22.1.0
Requires-Dist: backoff==2.2.1
Requires-Dist: beautifulsoup4==4.11.2
Requires-Dist: docx2txt==0.8
Requires-Dist: e2b==0.10.6
Requires-Dist: ffmpeg==1.4
Requires-Dist: flask==3.0.0
Requires-Dist: google-api-python-client==2.85.0
Requires-Dist: langchain==0.0.335
Requires-Dist: llama-index==0.8.69.post1
Requires-Dist: nltk==3.8.1
Requires-Dist: openai==1.2.0
Requires-Dist: pillow==9.3.0
Requires-Dist: pinecone-client==2.1.0
Requires-Dist: protobuf==3.20.2
Requires-Dist: py-cord==2.4.1
Requires-Dist: pycord-multicog==1.0.2
Requires-Dist: pydantic==2.4.2
Requires-Dist: pypdf==3.11.1
Requires-Dist: pytest-asyncio==0.21.0
Requires-Dist: pytest~=7.2.2
Requires-Dist: python-dotenv==1.0.0
Requires-Dist: python-pptx==0.6.21
Requires-Dist: replicate==0.15.4
Requires-Dist: requests==2.31.0
Requires-Dist: sentencepiece==0.1.99
Requires-Dist: sqlitedict==2.1.0
Requires-Dist: tiktoken==0.4.0
Requires-Dist: tqdm==4.64.1
Requires-Dist: transformers==4.25.1
Requires-Dist: unidecode==1.3.6
Requires-Dist: werkzeug==3.0.1
Requires-Dist: wolframalpha==5.0.0
Requires-Dist: youtube-transcript-api==0.5.0
Requires-Dist: yt-dlp==2023.3.4
Provides-Extra: full
Requires-Dist: ffmpeg-python==0.2.0; extra == 'full'
Requires-Dist: huggingface-hub==0.12.1; extra == 'full'
Requires-Dist: more-itertools==9.0.0; extra == 'full'
Requires-Dist: numpy==1.24.2; extra == 'full'
Requires-Dist: openai-whisper; extra == 'full'
Requires-Dist: scipy==1.10.1; extra == 'full'
Requires-Dist: sentence-transformers==2.2.2; extra == 'full'
Requires-Dist: tokenizers==0.13.3; extra == 'full'
Requires-Dist: torch==1.13.1; extra == 'full'
Requires-Dist: torchvision==1.14.1; extra == 'full'
